b_dynamodb_common/__init__.py
b_dynamodb_common/attributes/__init__.py
b_dynamodb_common/attributes/fernet_attribute.py
b_dynamodb_common/attributes/kms_attribute.py
b_dynamodb_common/encoders/__init__.py
b_dynamodb_common/encoders/dynamodb_encoder.py
b_dynamodb_common/encoders/pynamodb_encoder.py
b_dynamodb_common/models/__init__.py
b_dynamodb_common/models/model_type_factory.py
b_dynamodb_common/models/permission_model.py
b_dynamodb_common/seeds/__init__.py
b_dynamodb_common/seeds/random_data_seeder.py
b_dynamodb_common/utils/__init__.py
b_dynamodb_common/utils/pynamodb_list_function.py
b_dynamodb_common/utils/pynamodb_list_result.py
b_dynamodb_common_test/integration/__init__.py
b_dynamodb_common_test/integration/app.py
b_dynamodb_common_test/integration/conftest.py
b_dynamodb_common_test/integration/infrastructure.py
b_dynamodb_common_test/integration/fixtures/__init__.py
b_dynamodb_common_test/integration/fixtures/dummy_entity.py
b_dynamodb_common_test/integration/tests/__init__.py
b_dynamodb_common_test/integration/tests/attributes/__init__.py
b_dynamodb_common_test/integration/tests/attributes/test_fernet_attribute.py
b_dynamodb_common_test/integration/tests/attributes/test_kms_attribute.py
b_dynamodb_common_test/integration/tests/encoders/__init__.py
b_dynamodb_common_test/integration/tests/encoders/test_dynamodb_encoder.py
b_dynamodb_common_test/integration/tests/encoders/test_pynamodb_encoder.py
b_dynamodb_common_test/integration/tests/models/__init__.py
b_dynamodb_common_test/integration/tests/models/test_model_type_factory.py
b_dynamodb_common_test/integration/tests/models/test_permission_model.py
b_dynamodb_common_test/integration/tests/seeds/__init__.py
b_dynamodb_common_test/integration/tests/utils/__init__.py
b_dynamodb_common_test/integration/tests/utils/test_pynamodb_list_function.py
b_dynamodb_common_test/integration/tests/utils/test_pynamodb_list_result.py
b_dynamodb_common_test/unit/__init__.py
b_dynamodb_common-0.4.1.dist-info/LICENSE
b_dynamodb_common-0.4.1.dist-info/METADATA
b_dynamodb_common-0.4.1.dist-info/WHEEL
b_dynamodb_common-0.4.1.dist-info/top_level.txt
b_dynamodb_common-0.4.1.dist-info/RECORD
