Metadata-Version: 2.1
Name: b-dynamodb-common
Version: 0.4.1
Summary: Common functionality for interacting with dynamodb easier. Most of the functionality is based on PynamoDB ORM library.
Home-page: https://github.com/biomapas/B.DynamoDbCommon.git
License: Apache License 2.0
Keywords: AWS DynamoDB PynamoDB Database ORM Python
Platform: UNKNOWN
Classifier: Programming Language :: Python :: 3
Classifier: Operating System :: OS Independent
Requires-Dist: pynamodb (<6.0.0,>=5.0.0)
Requires-Dist: cryptography (<38.0.0,>=35.0.0)
Requires-Dist: ordered-set (<5.0.0,>=4.0.0)
